__init__.py
celltraj_1apr21.py
cli.py
features.py
imageprep.py
model.py
trajectory.py
trajectory_legacy.py
translate.py
utilities.py
celltraj_copperma-0.1.0.dist-info/AUTHORS.rst
celltraj_copperma-0.1.0.dist-info/LICENSE
celltraj_copperma-0.1.0.dist-info/METADATA
celltraj_copperma-0.1.0.dist-info/WHEEL
celltraj_copperma-0.1.0.dist-info/top_level.txt
celltraj_copperma-0.1.0.dist-info/RECORD
