Metadata-Version: 2.1
Name: celltraj_copperma
Version: 0.1.0
Summary: Toolset for single-cell trajectory modeling.
Author-email: Jeremy Copperman <copperma@ohsu.edu>
Project-URL: Homepage, https://github.com/jcopperm/celltraj
Project-URL: Issues, https://github.com/jcopperm/celltraj/issues
Classifier: Programming Language :: Python :: 3
Classifier: License :: OSI Approved :: MIT License
Classifier: Operating System :: OS Independent
Requires-Python: >=3.5
License-File: LICENSE
License-File: AUTHORS.rst
Requires-Dist: numpy
Requires-Dist: h5py
Requires-Dist: matplotlib
Requires-Dist: pyemma
Requires-Dist: scipy
Requires-Dist: scikit-image
Requires-Dist: scikit-learn
Requires-Dist: pystackreg
Provides-Extra: dependencies
Requires-Dist: mahotas ; extra == 'dependencies'
Requires-Dist: umap-learn ; extra == 'dependencies'
Requires-Dist: pytorch ; extra == 'dependencies'
Requires-Dist: pandas ; extra == 'dependencies'
Requires-Dist: dask ; extra == 'dependencies'
Requires-Dist: msmtools ; extra == 'dependencies'
Requires-Dist: csaps ; extra == 'dependencies'
Requires-Dist: pygpcca ; extra == 'dependencies'
Requires-Dist: btrack ; extra == 'dependencies'
Requires-Dist: adjustText ; extra == 'dependencies'
Requires-Dist: cmapfile ; extra == 'dependencies'
